PyEZNet/Activation_Function.py
PyEZNet/DataLoader.py
PyEZNet/Diff_Func.py
PyEZNet/LOSS_FUNC.py
PyEZNet/Layer.py
PyEZNet/Net.py
PyEZNet/PreProcessing_data.py
PyEZNet/__init__.py
PyEZNet/utils.py
PyNNN/Activation_Function.py
PyNNN/DataLoader.py
PyNNN/Diff_Func.py
PyNNN/LOSS_FUNC.py
PyNNN/Layer.py
PyNNN/Net.py
PyNNN/PreProcessing_data.py
PyNNN/__init__.py
PyNNN/utils.py
PyEZNet-0.0.1.dist-info/METADATA
PyEZNet-0.0.1.dist-info/WHEEL
PyEZNet-0.0.1.dist-info/top_level.txt
PyEZNet-0.0.1.dist-info/RECORD
