Metadata-Version: 2.1
Name: PyEZNet
Version: 0.0.1
Summary: A neural network framework based on numpy only
Home-page: https://github.com/EslamAsfour/PyNNN
Author: Ahmed Khaled
Author-email: ahmedkhaled11119999@gmail.com
License: UNKNOWN
Platform: UNKNOWN
Classifier: License :: OSI Approved :: MIT License
Requires-Python: >=3.6
Requires-Dist: numpy
